{
  "gouvernorats": [
    {
      "nom": "Tunis",
      "délégations": ["Bab El Bhar", "Bab Souika", "Carthage","Cité El Khadra",
       "Djebel Jelloud","El Kabaria","El Menzah","El Omrane","El Omrane supérieur",
       "El Ouardia","Ettahrir","Ezzouhour","Hraïria","La Goulette","La Marsa","Le Bardo",
       "Le Kram","La Médina","Séjoumi","Sidi El Béchir","Sidi Hassine"]
    },
    {
      "nom": "Sousse",
      "délégations": ["Akouda","Bouficha","Enfida","Hammam Sousse",
        "Hergla","Kalâa Kebira", "Kalâa Seghira","Kondar","Msaken",
        "Sidi Bou Ali","Sidi El Hani","Sousse Jawhara","Sousse Médina",
        "Sousse Riadh", "Sousse Sidi Abdelhamid"]    
    },
    {
      "nom": "Sfax",
      "délégations": [" Agareb ", "Bir Ali Ben Khalifa", "El Amra","El Hencha",
        "Graïba ","Jebiniana"," Kerkennah","Mahrès",
        "Menzel Chaker","Sakiet Eddaïer","Sakiet Ezzit","Sfax Ouest","Sfax Sud",
        "Sfax Ville","Skhira","Thyna"]
    },
    {
      "nom": "Monastir",
      "délégations": [" Bekalta ", "Bembla", "Beni Hassen","Jemmal",
        "Ksar Hellal ","Ksibet el-Médiouni"," Moknine","Monastir",
        "Ouerdanine","Sahline","Sayada-Lamta-Bou Hajar","Téboulba","Zéramdine"]
    },
    {
      "nom": "Gabès",
      "délégations": [" Gabès Médina ", "Gabès Ouest", "Gabès Sud","Ghannouch",
        "El Hamma","Matmata"," Mareth","Menzel El Habib",
        "Métouia","Nouvelle Matmata"]
    },
    {
      "nom": "Bizerte",
      "délégations": [" Bizerte Nord ", "Bizerte Sud", "El Alia","Ghar El Melh",
        "Ghezala ","Joumine","Mateur","Menzel Bourguiba",
        "Menzel Jemil","Ras Jebel","Sejnane","Tinja","Utique","Zarzouna"]
    },
    {
      "nom": "Kairouan",
      "délégations": [" Bou Hajla ", "Chebika", "Echrarda","El Alâa",
        "Haffouz","Hajeb El Ayoun"," Kairouan Nord","Kairouan Sud",
        "Nasrallah","Oueslatia","Sbikha"]
    },
    {
      "nom": "Gafsa",
      "délégations": [" Belkhir ", "El Guettar", "El Ksar","Gafsa Nord",
        "Gafsa Sud ","Mdhilla"," Métlaoui","Moularès",
        "Redeyef","Sened","Sidi Aïch"]
    },
    {
      "nom": "Nabeul",
      "délégations": [" Béni Khalled ", "Béni Khiar", "Bou Argoub","Dar Chaâbane El Fehri",
        "El Haouaria ","El Mida"," Grombalia","Hammam Ghezèze",
        "Hammamet","Kélibia","Korba","Menzel Bouzelfa","Menzel Temime","Nabeul","Soliman","Takelsa"]
    },
    {
      "nom": "Tataouine",
      "délégations": [" Bir Lahmar ", "Dehiba", "Ghomrassen","Remada",
        "Smâr","Tataouine Nord"," Tataouine Sud"]
    },
    {
      "nom": "Mahdia",
      "délégations": [" Bou Merdes", "Chebba", "Chorbane","El Jem",
        "Essouassi ","Hebira"," Ksour Essef","Mahdia",
        "Melloulèche","Ouled Chamekh","Sidi Alouane","Rejiche","El Bradâa"]
    },
    {
      "nom": "Kasserine",
      "délégations": [" El Ayoun ", "Ezzouhour", "Fériana","Foussana",
        "Haïdra ","Hassi El Ferid"," Jedelienne","Kasserine Nord",
        "Kasserine Sud","Majel Bel Abbès","Sbeïtla","Sbiba","Thala"]
    },
    {
      "nom": "Médenine",
      "délégations": [" Ben Gardane ", "Beni Khedache", "Djerba-Ajim","Djerba-Houmt Souk",
        "Djerba-Midoun","Médenine Nord"," Médenine Sud","Sidi Makhlouf",
        "Zarzis"]
    },
    {
      "nom": "Beja",
      "délégations": ["Goubellat","Medjez el-Beb ","Nefza","Testour",
        "Thibar","Beja", "Maagoula", "Sidi Ismail"]
    },
    {
      "nom": "Ben Arous",
      "délégations": [" Ben Arous", "Bou Mhel el-Bassatine", "El mourouj","Ezzahra",
        "Fouchana ","Hammam Chott","Hammam Lif","Mohamedia",
        "Medina Jedida","Mégrine","Mornag","Radès"]
    },
    {
      "nom": "Manouba",
      "délégations": [" La Manouba ", "Den Den", "Douar Hicher","Oued Ellil",
        "Mornaguia","Borj El Amri"," Djedeida","Tebourba",
        "El Batan"]
    },
    {
      "nom": "Siliana",
      "délégations": [" Bargou ", "bou Arada", "El Aroussa","El Krib",
        "Gaâfour ","Kesra"," Makthar","Rouhia",
        "Sidi Bou Rouis","Siliana Nord","Siliana Sud"]
    },
    {
      "nom": "Zaghouan",
      "délégations": [" Bir Mcherga ", "El Fahs", "Nadhour","Saouaf",
        "Zaghouan ","Zriba"]
    },
    {
      "nom": "Jendouba",
      "délégations": [" Aïn Draham", "Balta-Bou Aouane", "Bou Salem","Fernana",
        "Ghardimaou ","Jendouba Sud"," Jendouba Nord","Oued Meliz",
        "Tabarka"]
    },
    {
      "nom": "Tozeur",
      "délégations": [" Degache", "Hazoua", "Nefta","Tameghza",
        "Tozeur"]
    },
    {
      "nom": "Kébili",
      "délégations": [" Douz Nord ", "Douz Sud", "Faouar","Kébili Nord",
        "Kébili Sud","Souk Lahad"]
    },
    {
      "nom": "Ariana",
      "délégations": ["Ariana", "Cite Ettadhamen", "Kalaat Andalous","Mnihila",
        "Raoued", "Sidi Thabet", "Soukra"]
    }
  
  ]
}